{
    "relationships": [
        {
            "relationshipId": 1,
            "relationshipName": "requester",
            "otherEntityName": "user",
            "relationshipType": "many-to-one",
            "otherEntityField": "login"
        },
        {
            "relationshipId": 2,
            "relationshipName": "requested",
            "otherEntityName": "user",
            "relationshipType": "many-to-one",
            "otherEntityField": "login"
        }
    ],
    "fields": [
        {
            "fieldId": 1,
            "fieldName": "sentDateAndTime",
            "fieldType": "ZonedDateTime",
            "fieldValidateRules": [
                "required"
            ]
        },
        {
            "fieldId": 2,
            "fieldName": "isAccepted",
            "fieldType": "Boolean",
            "fieldValidateRules": [
                "required"
            ]
        },
        {
            "fieldId": 3,
            "fieldName": "acceptedDateAndTime",
            "fieldType": "ZonedDateTime",
            "fieldValidateRules": []
        }
    ],
    "changelogDate": "20160127112022",
    "dto": "no",
    "service": "no",
    "pagination": "no"
}